<?xml version="1.0" encoding="us-ascii"?>
<Attributes Version="31">
	<Attr name="console_mode_chosen" value="0" />
	<Attr name="controller_adaptiveTriggerEffect" value="true" />
	<Attr name="controller_deadZone" value="0.2" />
	<Attr name="controller_immersiveTriggerEffect" value="true" />
	<Attr name="controller_invertHorizontal" value="0" />
	<Attr name="controller_invertVertical" value="0" />
	<Attr name="controller_lightBarEffect" value="true" />
	<Attr name="controller_sensitivityHorizontal" value="45" />
	<Attr name="controller_sensitivityVertical" value="45" />
	<Attr name="controller_vibrations" value="true" />
	<Attr name="controls_invertMouse" value="0" />
	<Attr name="controls_sensitivity" value="45" />
	<Attr name="eula_confirmed_version" value="1" />
	<Attr name="fov" value="63.0883" />
	<Attr name="fps" value="0" />
	<Attr name="g_language" value="chineses" />
	<Attr name="g_telemetry" value="true" />
	<Attr name="gamma" value="0" />
	<Attr name="hfov" value="95" />
	<Attr name="keybinds_settings" value="&lt;keybinds /&gt;&#10;" />
	<Attr name="r_AntialiasingMode" value="3" />
	<Attr name="r_MotionBlur" value="0" />
	<Attr name="refresh_rate" value="3" />
	<Attr name="res_fs" value="2" />
	<Attr name="res_quality" value="0" />
	<Attr name="res_x" value="3840" />
	<Attr name="res_y" value="2160" />
	<Attr name="sound_master" value="1" />
	<Attr name="sound_music" value="1" />
	<Attr name="sound_sound" value="1" />
	<Attr name="sys_spec_Characters" value="5" />
	<Attr name="sys_spec_GlobalIllumination" value="3" />
	<Attr name="sys_spec_Light" value="4" />
	<Attr name="sys_spec_ObjectDetail" value="4" />
	<Attr name="sys_spec_Particles" value="4" />
	<Attr name="sys_spec_PostProcessing" value="4" />
	<Attr name="sys_spec_Shading" value="4" />
	<Attr name="sys_spec_Shadows" value="3" />
	<Attr name="sys_spec_Texture" value="5" />
	<Attr name="sys_spec_Vegetation" value="4" />
	<Attr name="sys_spec_VolumetricEffects" value="4" />
	<Attr name="telemetry_confirmed" value="1" />
	<Attr name="upscalingMode" value="0" />
	<Attr name="upscalingSharpness" value="0.5" />
	<Attr name="upscalingTechnology" value="2" />
	<Attr name="vsync" value="0" />
	<Attr name="wh_cl_NearDof" value="0" />
	<Attr name="wh_horse_RoadMagnetism" value="1" />
	<Attr name="wh_ui_BubblesEnabled" value="true" />
	<Attr name="wh_ui_EnableSubtitleBg" value="false" />
	<Attr name="wh_ui_EnableSubtitleSpeakerName" value="false" />
	<Attr name="wh_ui_ShowNormalCursor" value="false" />
	<Attr name="wh_ui_SubtitleSize" value="0" />
	<Attr name="wh_ui_SubtitlesEnabled" value="true" />
	<Attr name="wh_ui_TutorialsEnabled" value="true" />
</Attributes>